CHANGELOG.rst
LICENSE.txt
MANIFEST.in
README.rst
requirements.txt
setup.py
btcndash/__init__.py
btcndash/btcndash.py
btcndash/config.json
btcndash/logger.py
btcndash/page_cache.py
btcndash/worker.py
btcndash.egg-info/PKG-INFO
btcndash.egg-info/SOURCES.txt
btcndash.egg-info/dependency_links.txt
btcndash.egg-info/entry_points.txt
btcndash.egg-info/not-zip-safe
btcndash.egg-info/requires.txt
btcndash.egg-info/top_level.txt
btcndash/static/css/bootstrap.css
btcndash/static/css/font-style.css
btcndash/static/css/main.css
btcndash/static/css/table.css
btcndash/static/fonts/linecons.eot
btcndash/static/fonts/linecons.svg
btcndash/static/fonts/linecons.ttf
btcndash/static/fonts/linecons.woff
btcndash/static/img/bitcoin_logo_qt.png
btcndash/static/img/blocklogo.png
btcndash/static/img/favicon.ico
btcndash/static/img/sep-half.png
btcndash/static/js/bootstrap.js
btcndash/static/js/highcharts-4.2.3.min.js
btcndash/static/js/jquery-1.12.2.min.js
btcndash/static/js/jquery.dataTables.min.js
btcndash/views/404.tpl
btcndash/views/bandwidth.tpl
btcndash/views/bandwidth_summary.tpl
btcndash/views/base.tpl
btcndash/views/bitnodes.tpl
btcndash/views/blank.tpl
btcndash/views/connections.tpl
btcndash/views/donate.tpl
btcndash/views/donate2.tpl
btcndash/views/fees.tpl
btcndash/views/general.tpl
btcndash/views/general2.tpl
btcndash/views/index.tpl
btcndash/views/mempool.tpl
btcndash/views/network.tpl
btcndash/views/nodedetails.tpl
btcndash/views/peers.tpl
btcndash/views/peers2.tpl
btcndash/views/tx.tpl
btcndash/views/tx2.tpl
doc/Makefile
doc/btcndash_screenshot.png
doc/changelog_link.rst
doc/conf.py
doc/configuration.rst
doc/customization.rst
doc/index.rst
doc/installation.rst
scripts/bitcoin.conf
scripts/bitcoind
scripts/bitcoind.conf
scripts/btcndash.conf
scripts/btcndash.service
scripts/create user commands.txt
scripts/deploy commands.txt