Metadata-Version: 1.1
Name: btcndash
Version: 2.3.3
Summary: Lightweight status dashboard for Bitcoin nodes.
Home-page: https://bitbucket.org/mattdoiron/btcndash
Author: Matt Doiron
Author-email: mattdoiron@gmail.com
License: GPL3
Download-URL: https://bitbucket.org/mattdoiron/btcndash/downloads/
Keywords: bitcoin node dashboard fullnode
Platform: any
Classifier: Programming Language :: Python :: 2.7
Classifier: Programming Language :: Python :: 3.5
Classifier: Development Status :: 4 - Beta
Classifier: Natural Language :: English
Classifier: Environment :: Web Environment
Classifier: License :: OSI Approved :: GNU General Public License v3 (GPLv3)
